{
    "ipaddress":"localhost",
    "port":9995,
	"datahubActionUri": "http://datahub.io/api/3/action/",
	"mappingConfigPath": "MappingConfig.json",
	"ckanTimeOut": 10000,
    "adminName":"aksw",
    "password":"goodStuff",
    "virtuosoHost" : "vmdbpedia.informatik.uni-leipzig.de",
    "virtuosoPort" : 1111,
    "virtuosoUser" : "dataid",
    "virtuosoPass" : "akswska",
	"ckanActionMap":{
		"GetDataset": "package_show",
		"CreateDataset": "package_create",
		"UpdateDataset": "package_update",
        "GetRelationships": "package_relationships_list",
        "UpdateDatasetRelationship": "package_create",
        "CreateDatasetRelationship": "package_relationship_create",
        "GetOrganizationId": "organization_show"
	},
    "ontologyMap":{
      "dataid": {"uri":"http://dataid.dbpedia.org/ns/core#", "dlUrl":"http://localhost:9995/static/ontology.ttl"},
      "void": {"uri":"http://rdfs.org/ns/void#", "dlUrl":"http://localhost:9995/static/void.rdf"}
    },
  "exceptionMap":{
    "http://rdfunit.aksw.org/data/generators#OWLQCARDEX": ["http://rdfs.org/ns/void#objectsTarget"],
    "http://rdfunit.aksw.org/data/generators#OWLQCARDEX-MIN":["http://www.w3.org/ns/dcat#landingPage"]
  }
}